Metadata-Version: 1.0
Name: lizzie136-distributions
Version: 0.1
Summary: Gaussian and Binomial distributions
Home-page: UNKNOWN
Author: Elizabeth Margolis
Author-email: darknessover136@gmail.com
License: UNKNOWN
Platform: UNKNOWN
